LICENSE
README
async_cast.py
setup.py
async_cast.egg-info/PKG-INFO
async_cast.egg-info/SOURCES.txt
async_cast.egg-info/dependency_links.txt
async_cast.egg-info/requires.txt
async_cast.egg-info/top_level.txt