Metadata-Version: 2.1
Name: async-cast
Version: 0.6.2
Summary: Cast an async function to blocking function and viceversa. Also use threads pools if needed.
Home-page: https://github.com/joaduo/async_cast
Author: Joaquin Duo
Author-email: joaduo@gmail.com
License: MIT
Keywords: asyncio,async,sync,casting,threads
Platform: UNKNOWN
License-File: LICENSE
